emfuzzer/__init__.py
emfuzzer/__main__.py
emfuzzer/arguments.py
emfuzzer/case.py
emfuzzer/coap/__init__.py
emfuzzer/coap/code.py
emfuzzer/coap/validator.py
emfuzzer/config.py
emfuzzer/context.py
emfuzzer/delay.py
emfuzzer/injector/__init__.py
emfuzzer/injector/subprocess.py
emfuzzer/injector/subtask.py
emfuzzer/io/__init__.py
emfuzzer/io/net.py
emfuzzer/io/sockets.py
emfuzzer/io/streams.py
emfuzzer/results/__init__.py
emfuzzer/results/basic.py
emfuzzer/ssh/__init__.py
emfuzzer/ssh/connectionconfig.py
emfuzzer/ssh/invoker.py
emfuzzer/ssh/reader.py
emfuzzer/subtasks/__init__.py
emfuzzer/subtasks/ping.py
emfuzzer/subtasks/remote.py
emfuzzer/subtasks/subprocess.py
emfuzzer/subtasks/subtask.py
emfuzzer/version.py
emfuzzer-1.0.0.dist-info/LICENSE.txt
emfuzzer-1.0.0.dist-info/METADATA
emfuzzer-1.0.0.dist-info/WHEEL
emfuzzer-1.0.0.dist-info/entry_points.txt
emfuzzer-1.0.0.dist-info/RECORD
