Metadata-Version: 2.3
Name: emfuzzer
Version: 1.0.0
Summary: Fuzzing experiments orchestrator for embedded systems
License: MIT
Keywords: embedded,fuzzing,testing,experiments
Author: Konrad Grochowski
Author-email: Konrad.Grochowski@pw.edu.pl
Requires-Python: >= 3.13
Classifier: Development Status :: 4 - Beta
Classifier: Environment :: Console
Classifier: Intended Audience :: Developers
Classifier: Intended Audience :: Information Technology
Classifier: Intended Audience :: Science/Research
Classifier: License :: OSI Approved :: MIT License
Classifier: Operating System :: POSIX :: Linux
Classifier: Programming Language :: Python :: 3.13
Classifier: Topic :: Software Development :: Embedded Systems
Classifier: Topic :: Software Development :: Testing
Requires-Dist: paramiko (==3.5.1)
Project-URL: ChangeLog, https://github.com/ZBOSK-II/emfuzzer/blob/master/CHANGELOG.md
Project-URL: GitHub, https://github.com/ZBOSK-II/emfuzzer
